README.md
setup.py
BaryonForge/__init__.py
BaryonForge.egg-info/PKG-INFO
BaryonForge.egg-info/SOURCES.txt
BaryonForge.egg-info/dependency_links.txt
BaryonForge.egg-info/not-zip-safe
BaryonForge.egg-info/requires.txt
BaryonForge.egg-info/top_level.txt
BaryonForge/Profiles/BaryonCorrection.py
BaryonForge/Profiles/Battaglia.py
BaryonForge/Profiles/Schneider19.py
BaryonForge/Profiles/Thermodynamic.py
BaryonForge/Profiles/__init__.py
BaryonForge/Runners/HealpixRunner.py
BaryonForge/Runners/Map2DRunner.py
BaryonForge/Runners/SnapshotRunner.py
BaryonForge/Runners/__init__.py
BaryonForge/utils/Parallelize.py
BaryonForge/utils/Pixel.py
BaryonForge/utils/Tabulate.py
BaryonForge/utils/__init__.py
BaryonForge/utils/debug.py
BaryonForge/utils/io.py
BaryonForge/utils/misc.py