Metadata-Version: 2.1
Name: BaryonForge
Version: 1.0.0
Summary: A pipeline for adding baryonic imprints and thermodynamic maps to N-body simulations
Home-page: https://github.com/DhayaaAnbajagane/BaryonForge
Author: Dhayaa Anbajagane
Author-email: dhayaa@uchicago.edu
Classifier: Programming Language :: Python :: 3
Classifier: License :: OSI Approved :: MIT License
Classifier: Operating System :: OS Independent
Requires-Python: >=3.6
